sentor/__init__.py
sentor/client.py
sentor/exceptions.py
tests/__init__.py
tests/test_client.py
sentor_ml-1.4.0.dist-info/METADATA
sentor_ml-1.4.0.dist-info/WHEEL
sentor_ml-1.4.0.dist-info/entry_points.txt
sentor_ml-1.4.0.dist-info/top_level.txt
sentor_ml-1.4.0.dist-info/RECORD
